mdai/.DS_Store
mdai/__init__.py
mdai/client.py
mdai/inference.py
mdai/preprocess.py
mdai/utils/__init__.py
mdai/utils/common_utils.py
mdai/utils/dicom_utils.py
mdai/utils/keras_utils.py
mdai/utils/sample_SR.dcm
mdai/utils/sample_dicom.dcm
mdai/utils/tensorflow_utils.py
mdai/utils/transforms.py
mdai/visualize.py
mdai-0.15.1.dist-info/LICENSE
mdai-0.15.1.dist-info/METADATA
mdai-0.15.1.dist-info/WHEEL
mdai-0.15.1.dist-info/RECORD
