Metadata-Version: 2.1
Name: mdai
Version: 0.15.1
Summary: MD.ai Python client library
Home-page: https://github.com/mdai/mdai-client-py
License: Apache-2.0
Author: MD.ai
Author-email: github@md.ai
Requires-Python: >=3.8
Classifier: Intended Audience :: Developers
Classifier: Intended Audience :: Education
Classifier: Intended Audience :: Healthcare Industry
Classifier: Intended Audience :: Science/Research
Classifier: License :: OSI Approved :: Apache Software License
Classifier: Programming Language :: Python :: 3
Classifier: Programming Language :: Python :: 3.8
Classifier: Programming Language :: Python :: 3.9
Classifier: Programming Language :: Python :: 3.10
Classifier: Programming Language :: Python :: 3.11
Classifier: Programming Language :: Python :: 3.12
Classifier: Programming Language :: Python :: 3.13
Classifier: Topic :: Scientific/Engineering :: Artificial Intelligence
Classifier: Topic :: Scientific/Engineering :: Medical Science Apps.
Classifier: Topic :: Software Development :: Libraries
Classifier: Topic :: Software Development :: Libraries :: Python Modules
Requires-Dist: PyYAML (>=6.0.2,<7.0.0)
Requires-Dist: arrow (>=1.3.0,<2.0.0)
Requires-Dist: dicom2nifti (<2.6.0)
Requires-Dist: matplotlib (>=3.7.3,<4.0.0)
Requires-Dist: nibabel (>=5.2.1,<6.0.0)
Requires-Dist: numpy (>=1.24.0,<2.0.0)
Requires-Dist: opencv-python (>=4.8.1.78,<5.0.0.0)
Requires-Dist: pandas (>=2.0.0,<3.0.0)
Requires-Dist: pillow (>=10.0.0,<11.0.0)
Requires-Dist: pydicom (>=2.4.0,<3.0.0)
Requires-Dist: requests (>=2.32.0,<3.0.0)
Requires-Dist: retrying (>=1.3.4,<2.0.0)
Requires-Dist: scikit-image (>=0.21.0,<1.0.0)
Requires-Dist: tqdm (>=4.66.5,<5.0.0)
Project-URL: Documentation, https://docs.md.ai/annotator/python/installation/
Project-URL: Repository, https://github.com/mdai/mdai-client-py
